README.md
setup.py
mysqlSaver/__init__.py
mysqlSaver/checkerandreceiver.py
mysqlSaver/connection.py
mysqlSaver/creator.py
mysqlSaver/keymanager.py
mysqlSaver/partition.py
mysqlSaver/saver.py
mysqlSaver.egg-info/PKG-INFO
mysqlSaver.egg-info/SOURCES.txt
mysqlSaver.egg-info/dependency_links.txt
mysqlSaver.egg-info/requires.txt
mysqlSaver.egg-info/top_level.txt