Metadata-Version: 2.1
Name: mysqlSaver
Version: 0.2.7
Summary: This Is MySQL Package That You Can Save DataFrame As Table, Partition, Update , Primarykey And Unique In MySQL
Author: Kasra Khaksar
Author-email: kasrakhaksar17@gmail.com
Requires-Python: >=3.9
